pybluezi/array/__init__.py
pybluezi/array/_dynamic_array.py
pybluezi/deque/__init__.py
pybluezi/deque/_array_deque.py
pybluezi/queue/__init__.py
pybluezi/queue/_array_queue.py
pybluezi/stack/__init__.py
pybluezi/stack/_array_stack.py
pybluezi-0.9.0.dist-info/METADATA
pybluezi-0.9.0.dist-info/WHEEL
pybluezi-0.9.0.dist-info/licenses/LICENCE
pybluezi-0.9.0.dist-info/RECORD
