Metadata-Version: 2.1
Name: pybluezi
Version: 0.9.0
Summary: An educational collection-like package
Project-URL: HomePage, https://github.com/ImYod4/zi
Author-email: Yoda <im.yod4@gmail.com>
License-File: LICENCE
